auto_coverage_report/__init__.py
auto_coverage_report/command_line.py
tests/__init__.py
tests/test_runtests.py
auto_coverage_report-0.0.2.dist-info/LICENSE.md
auto_coverage_report-0.0.2.dist-info/METADATA
auto_coverage_report-0.0.2.dist-info/WHEEL
auto_coverage_report-0.0.2.dist-info/entry_points.txt
auto_coverage_report-0.0.2.dist-info/top_level.txt
auto_coverage_report-0.0.2.dist-info/RECORD
