Metadata-Version: 2.1
Name: auto-coverage-report
Version: 0.0.2
Summary: A auto tester coverage report
Home-page: http://github.com/silviolleite/test-coverage-report
Author: Silvio Luis
Author-email: silviolleite@gmail.com
Maintainer: David Guimarães
Maintainer-email: dvdgmf@gmail.com
License: MIT License
Platform: UNKNOWN
Classifier: Environment :: Console
Classifier: Intended Audience :: Developers
Classifier: License :: OSI Approved :: MIT License
Classifier: Operating System :: OS Independent
Classifier: Programming Language :: Python
Classifier: Programming Language :: Python :: 3
Classifier: Programming Language :: Python :: 3.4
Classifier: Programming Language :: Python :: 3.5
Classifier: Programming Language :: Python :: 3.6
Classifier: Programming Language :: Python :: 3.7
Classifier: Topic :: Utilities
Classifier: Topic :: Software Development
Classifier: Topic :: Software Development :: Testing
Classifier: Topic :: Software Development :: Testing :: Unit
Requires-Dist: coverage
Requires-Dist: pypandoc
